Metadata-Version: 1.0
Name: bi-ga-dist
Version: 1.0
Summary: Gaussian and Binomial distributions
Home-page: UNKNOWN
Author: Taha B Uyar
Author-email: UNKNOWN
License: UNKNOWN
Platform: UNKNOWN
